synthetic_dataset_generator-0.2.0.dist-info/METADATA
synthetic_dataset_generator-0.2.0.dist-info/WHEEL
synthetic_dataset_generator-0.2.0.dist-info/entry_points.txt
synthetic_dataset_generator-0.2.0.dist-info/licenses/LICENSE
synthetic_dataset_generator/__init__.py
synthetic_dataset_generator/__main__.py
synthetic_dataset_generator/_distiset.py
synthetic_dataset_generator/_inference_endpoints.py
synthetic_dataset_generator/_tabbedinterface.py
synthetic_dataset_generator/app.py
synthetic_dataset_generator/apps/__init__.py
synthetic_dataset_generator/apps/about.py
synthetic_dataset_generator/apps/base.py
synthetic_dataset_generator/apps/chat.py
synthetic_dataset_generator/apps/eval.py
synthetic_dataset_generator/apps/rag.py
synthetic_dataset_generator/apps/textcat.py
synthetic_dataset_generator/constants.py
synthetic_dataset_generator/pipelines/__init__.py
synthetic_dataset_generator/pipelines/base.py
synthetic_dataset_generator/pipelines/chat.py
synthetic_dataset_generator/pipelines/embeddings.py
synthetic_dataset_generator/pipelines/eval.py
synthetic_dataset_generator/pipelines/rag.py
synthetic_dataset_generator/pipelines/textcat.py
synthetic_dataset_generator/utils.py
synthetic_dataset_generator-0.2.0.dist-info/RECORD
