Metadata-Version: 2.1
Name: synthetic-dataset-generator
Version: 0.2.0
Summary: Build datasets using natural language
Keywords: gradio,synthetic-data,huggingface,argilla,generative-ai,ai
Author-Email: davidberenstein1957 <david.m.berenstein@gmail.com>
License: Apache 2
Requires-Python: <3.13,>=3.10
Requires-Dist: argilla<3.0.0,>=2.4.0
Requires-Dist: distilabel[argilla,hf-inference-endpoints,hf-transformers,instructor,llama-cpp,ollama,openai,outlines,vision,vllm]<2.00,>=1.5.0
Requires-Dist: gradio[oauth]<6.0.0,>=5.4.0
Requires-Dist: gradio-huggingfacehub-search<1.0.0,>=0.0.12
Requires-Dist: huggingface-hub<0.28.0,>=0.26.0
Requires-Dist: model2vec<1.0.0,>=0.2.4
Requires-Dist: nltk<4.0.0,>=3.9.1
Requires-Dist: pydantic<3.0.0,>=2.10.5
Requires-Dist: sentence-transformers<4.0.0,>=3.2.0
Requires-Dist: transformers<5.0.0,>=4.44.2
Requires-Dist: unstructured[docx,md,pdf]<1.0.0,>=0.16.3
Requires-Dist: setuptools
